sorcerun/__init__.py
sorcerun/auth_mongodb_option.py
sorcerun/cli.py
sorcerun/git_utils.py
sorcerun/globals.py
sorcerun/grid_plotter.py
sorcerun/incense_utils.py
sorcerun/mongodb_utils.py
sorcerun/plot.py
sorcerun/sacred_utils.py
sorcerun/slurm_utils.py
sorcerun/main/__init__.py
sorcerun/main/config.py
sorcerun/main/grid_config.py
sorcerun/main/main.py
sorcerun-0.5.18.data/scripts/flamegraph.pl
sorcerun-0.5.18.dist-info/licenses/LICENSE
sorcerun-0.5.18.dist-info/METADATA
sorcerun-0.5.18.dist-info/WHEEL
sorcerun-0.5.18.dist-info/entry_points.txt
sorcerun-0.5.18.dist-info/top_level.txt
sorcerun-0.5.18.dist-info/RECORD
